{
    "portfolios": [
      { "title": "Your GoTo List",
        "images": ["acai.jpg","coffee.jpg","pastries.jpg","fries.jpg","pancakes.jpg"],
        "id": "goto"
      },
      { "title": "Today is Taco Tuesday",
        "images": ["taco1.jpg","taco2.jpg","taco3.jpg","taco4.jpg","taco5.jpg"],
        "id": "today"
      },
      { "title": "Recommended for you",
        "images": ["eggs.jpg","sushi.jpg","toffee.jpg","macarons.jpg","salad.jpg"],
        "id": "recommended"
      },
      { "title": "Your friends recommend",
        "images": ["pho.jpg","donuts.jpg","scallops.jpg","ice-cream.jpg","cookies.jpg"],
        "id": "friend-recommended"
      }
    ],
    "cuisines": [
      {
        "id": "American",
        "image": "americanbutton.png"
      },
      {
        "id": "Mexican",
        "image": "mexicanbutton.png"
      },
      {
        "id": "Japanese",
        "image": "japanesebutton.png"
      },
      {
        "id": "Italian",
        "image": "italianbutton.png"
      },
      {
        "id": "Chinese",
        "image": " "
      },
      {
        "id": "French",
        "image": ""
      },
      {
        "id": "Brewery",
        "image": ""
      },
      {
        "id": "Fast Food",
        "image": ""
      },
      {
        "id": "Brazilian",
        "image": ""
      },
      {
        "id": "Indian",
        "image": ""
      },
      {
        "id": "Ethiopian",
        "image": ""
      },
      {
        "id": "Dessert",
        "image": ""
      }
    ],
    "profile-image": "profile-icon.png",
    "profile-name": "James Clark",
    "bio": "21 year old food enthusiast from San Diego. Let's go out to eat.",
    "myCuisines": ["Mexican", "Italian", "Japanese", "American"],
    "location": "San Diego",
    "profile-posts": [
      {
        "picture": true,
        "food-image": "jewel-roll.jpg",
        "restaurant": "@ShikuSushi",
        "restaurant-description": "The jewel roll was amazing!"
      },
      {
        "picture": false,
        "restaurant": "@BreakfastRepublic",
        "restaurant-description": "Get the flight of pancakes!"
      }
    ],
    "posts": [
      {
        "picture": true,
        "food-image": "french-toast.jpg",
        "name": "John Wilburn",
        "profile-image": "profile-icon.png",
        "restaurant": "@Snooze",
        "restaurant-description": "Loved the OMG french toast!"
      },
      {
        "picture": true,
        "food-image": "gelato.jpg",
        "name": "Jane Lee",
        "profile-image": "profile-icon.png",
        "restaurant": "@Pappalecco",
        "restaurant-description": "Pappalecco has the best gelato!"
      },
      {
        "picture": false,
        "name": "Mary Murphy",
        "profile-image": "profile-icon.png",
        "restaurant": "@NomadDonuts",
        "restaurant-description": "Nomad has the most unique donut flavors!"
      },
      {
        "picture": false,
        "name": "Alex Taylor",
        "profile-image": "profile-icon.png",
        "restaurant": "@AzukiSushi",
        "restaurant-description": "The Kobe roll is my favorite roll in San Diego!"
      },
    ],
      "restaurants":[
        {
          "id": "vallarta-express",
          "name": "Vallarta Express",
          "picture":"vallarta.jpg",
          "address":"4277 Genesee Ave (at Mt Edna Dr), San Diego, CA 92117",
          "cuisineId":"Mexican",
          "menu-items":[
            {
              "item-id":"carne_asada_fries",
              "item-name":"Carne Asada Fries",
              "item-image":"vallarta-carne_asada_fries.jpg"
            },
            {
              "item-id":"cali_burrito",
              "item-name":"California Burrito",
              "item-image":"vallarta-cali_burrito.jpg"
            },
            {
              "item-id":"shrimp_quesadilla",
              "item-name":"Shrimp Quesadilla",
              "item-image":"vallarta-shrimp_quesadilla.jpg"
            }
          ],
          "posts": [
            {
              "picture": true,
              "food-image": "vallarta-carne_asada.jpg",
              "name": "Smitty Werbenjagermanjensen",
              "profile-image": "profile-icon.png",
              "restaurant": "@vallarta-express",
              "restaurant-description": "Wow. #lit"
            },
            {
              "picture": true,
              "food-image": "vallarta-shrimp_quesadilla.jpg",
              "name": "Jane Lee",
              "profile-image": "profile-icon.png",
              "restaurant": "@vallarta-express",
              "restaurant-description": "Shrimpalicious."
            },
            {
              "picture": false,
              "name": "Mary Murphy",
              "profile-image": "profile-icon.png",
              "restaurant": "@vallarta-express",
              "restaurant-description": "The best 3am food."
            },
            {
              "picture": true,
              "food-image":"vallarta-cali_burrito.jpg",
              "name": "Alex Taylor",
              "profile-image": "profile-icon.png",
              "restaurant": "@vallarta-express",
              "restaurant-description": "oooo, there are fries in this!"
            },
          ]
        },
        {
          "id": "ki-sushi",
          "name": "Ki Sushi & Sake Bar",
          "picture":"ki.jpg",
          "address":"Costa Verde Shopping Ctr 8650 Genesee Ave, San Diego, CA 92122",
          "cuisineId":"Japanese",
          "menu-items":[
            {
              "item-id":"chicken_katsu",
              "item-name":"Chicken Katsu Bento",
              "item-image":"ki-chicken_katsu.jpg"
            },
            {
              "item-id":"sushi",
              "item-name":"Sushi Sampler",
              "item-image":"ki-sushi.jpg"
            },
            {
              "item-id":"miso_salmon",
              "item-name":"Miso Salmon",
              "item-image":"ki-miso_salmon.jpg"
            }
          ],
          "posts": [
            {
              "picture": true,
              "food-image": "ki-chicken_katsu.jpg",
              "name": "Smitty Werbenjagermanjensen",
              "profile-image": "profile-icon.png",
              "restaurant": "@ki-sushi",
              "restaurant-description": "more like chicken wowtsu."
            },
            {
              "picture": true,
              "food-image": "ki-sushi.jpg",
              "name": "Jane Lee",
              "profile-image": "profile-icon.png",
              "restaurant": "@ki-sushi",
              "restaurant-description": "sushisushisushi"
            },
            {
              "picture": false,
              "name": "Mary Murphy",
              "profile-image": "profile-icon.png",
              "restaurant": "@ki-sushi",
              "restaurant-description": "Good sake bombs."
            },
            {
              "picture": true,
              "food-image":"ki-miso_salmon.jpg",
              "name": "Alex Taylor",
              "profile-image": "profile-icon.png",
              "restaurant": "@ki-sushi",
              "restaurant-description": "The salmon is pretty good."
            },
          ]
        },
        {
          "id": "smash-burger",
          "name": "Smashburger",
          "picture":"smash.jpg",
          "address":"1555 Camino del Mar (at 15th St.), Del Mar, CA 92014, United States",
          "cuisineId":"American",
          "menu-items":[
            {
              "item-id":"chicken_sandwich",
              "item-name":"Classic Grilled Chicken Sandwich w/ Avocado",
              "item-image":"smash-chicken_sandwich.jpg"
            },
            {
              "item-id":"bbq",
              "item-name":"BBQ Burger",
              "item-image":"smash-bbq.jpg"
            },
            {
              "item-id":"black_bean",
              "item-name":"Black Bean Spicy Baja - Ultimate",
              "item-image":"smash-black_bean.jpg"
            }
          ],
          "posts": [
            {
              "picture": true,
              "food-image": "smash-bbq.jpg",
              "name": "Smitty Werbenjagermanjensen",
              "profile-image": "profile-icon.png",
              "restaurant": "@smash-burger",
              "restaurant-description": "The sauce is really good!"
            },
            {
              "picture": true,
              "food-image": "smash-chicken_sandwich.jpg",
              "name": "Jane Lee",
              "profile-image": "profile-icon.png",
              "restaurant": "@smash-burger",
              "restaurant-description": "so much food!"
            },
            {
              "picture": false,
              "name": "Mary Murphy",
              "profile-image": "profile-icon.png",
              "restaurant": "@smash-burger",
              "restaurant-description": "Staff is friendly."
            },
            {
              "picture": true,
              "food-image":"smash-black_bean.jpg",
              "name": "Alex Taylor",
              "profile-image": "profile-icon.png",
              "restaurant": "@smash-burger",
              "restaurant-description": "Perfect for vegetarians."
            },
          ]
        }
      ]
}
